doc/source/conf.py
src/mpl_bsic/__init__.py
src/mpl_bsic/mpl_bsic.py
bsic_utils-1.0.0.dist-info/METADATA
bsic_utils-1.0.0.dist-info/WHEEL
bsic_utils-1.0.0.dist-info/licenses/LICENSE
bsic_utils-1.0.0.dist-info/RECORD
