Metadata-Version: 2.1
Name: bsic_utils
Version: 1.0.0
Summary: BSIC's Utils Library
Project-URL: Homepage, https://github.com/pypa/sampleproject
Project-URL: Bug Tracker, https://github.com/pypa/sampleproject/issues
Author-email: Andrea Franceschini <andrea.franceschini03@gmail.com>
License-File: LICENSE
Classifier: License :: OSI Approved :: MIT License
Classifier: Operating System :: OS Independent
Classifier: Programming Language :: Python :: 3.12
Requires-Python: >=3.12
